as3nt/__init__.py
as3nt/core.py
as3nt/subenum.py
as3nt-1.1.0.dist-info/LICENSE
as3nt-1.1.0.dist-info/METADATA
as3nt-1.1.0.dist-info/WHEEL
as3nt-1.1.0.dist-info/entry_points.txt
as3nt-1.1.0.dist-info/top_level.txt
as3nt-1.1.0.dist-info/RECORD
